tech/aiotcloud/python/__init__.py
tech/aiotcloud/python/pyaiot.py
tech/aiotcloud/python/pyword.py
tech/aiotcloud/python/fonts/ASC16_8
tech/aiotcloud/python/fonts/ASC32_16
tech/aiotcloud/python/fonts/HZK12
tech/aiotcloud/python/fonts/HZK16
python_aiot_sdk-1.0.2.dist-info/METADATA
python_aiot_sdk-1.0.2.dist-info/WHEEL
python_aiot_sdk-1.0.2.dist-info/top_level.txt
python_aiot_sdk-1.0.2.dist-info/RECORD
