Metadata-Version: 2.1
Name: python-aiot-sdk
Version: 1.0.2
Summary: 智能物联云平台python sdk
Home-page: https://github.com/aiotcloud-tech/python-aiot-sdk
Author: sangxin
Author-email: 2876424407@qq.com
Maintainer: sangxin
Maintainer-email: 2876424407@qq.com
License: UNKNOWN
Platform: UNKNOWN
Requires-Dist: paho-mqtt
